fds/__init__.py
fds/sdk/__init__.py
fds/sdk/VectorData/__init__.py
fds/sdk/VectorData/api_client.py
fds/sdk/VectorData/configuration.py
fds/sdk/VectorData/exceptions.py
fds/sdk/VectorData/model_utils.py
fds/sdk/VectorData/rest.py
fds/sdk/VectorData/api/__init__.py
fds/sdk/VectorData/api/meta_api.py
fds/sdk/VectorData/api/vector_api.py
fds/sdk/VectorData/apis/__init__.py
fds/sdk/VectorData/model/__init__.py
fds/sdk/VectorData/model/chunk_text_response.py
fds/sdk/VectorData/model/chunk_text_response_meta.py
fds/sdk/VectorData/model/chunk_text_response_meta_pagination.py
fds/sdk/VectorData/model/chunk_text_result.py
fds/sdk/VectorData/model/document_types.py
fds/sdk/VectorData/model/document_types_response.py
fds/sdk/VectorData/model/error_object.py
fds/sdk/VectorData/model/error_response.py
fds/sdk/VectorData/model/meta.py
fds/sdk/VectorData/model/schemas.py
fds/sdk/VectorData/model/schemas_response.py
fds/sdk/VectorData/model/source.py
fds/sdk/VectorData/model/source_response.py
fds/sdk/VectorData/model/themes.py
fds/sdk/VectorData/model/themes_response.py
fds/sdk/VectorData/model/vector_data_request.py
fds/sdk/VectorData/model/vector_data_request_data.py
fds/sdk/VectorData/model/vector_data_response.py
fds/sdk/VectorData/model/vector_data_response_meta.py
fds/sdk/VectorData/model/vector_data_result.py
fds/sdk/VectorData/models/__init__.py
fds_sdk_vectordata-0.0.3.dist-info/licenses/LICENSE
fds_sdk_vectordata-0.0.3.dist-info/METADATA
fds_sdk_vectordata-0.0.3.dist-info/WHEEL
fds_sdk_vectordata-0.0.3.dist-info/top_level.txt
fds_sdk_vectordata-0.0.3.dist-info/RECORD
